[{"symbol":"COST","sector":"Consumer","open":1012.47,"high":1012.47,"low":1012.47,"close":1012.47,"volume":0,"timestamp":"2026-04-07 11:21:00","kafka_produce_time":1775575298826.0,"data_type":"real","event_time":"2026-04-07 11:21:00","date":"2026-04-07","_is_new":true,"moving_avg_5":1012.52,"moving_avg_20":1012.81,"volatility":0.0268,"rsi_14":45.96,"vwap":1014.95,"volume_trend":null,"price_change_pct":0.0,"crash_score":false,"spark_process_time":1775580781791,"latency_ms":5482965},{"symbol":"COST","sector":"Consumer","open":1012.53,"high":1012.53,"low":1012.53,"close":1012.53,"volume":0,"timestamp":"2026-04-07 11:21:00","kafka_produce_time":1775575353974.0,"data_type":"real","event_time":"2026-04-07 11:21:00","date":"2026-04-07","_is_new":true,"moving_avg_5":1012.52,"moving_avg_20":1012.8,"volatility":0.0268,"rsi_14":47.25,"vwap":1014.95,"volume_trend":null,"price_change_pct":0.0,"crash_score":false,"spark_process_time":1775580781791,"latency_ms":5427817},{"symbol":"COST","sector":"Consumer","open":1012.53,"high":1012.53,"low":1012.53,"close":1012.53,"volume":0,"timestamp":"2026-04-07 11:21:00","kafka_produce_time":1775575339093.0,"data_type":"real","event_time":"2026-04-07 11:21:00","date":"2026-04-07","_is_new":true,"moving_avg_5":1012.52,"moving_avg_20":1012.79,"volatility":0.0268,"rsi_14":47.25,"vwap":1014.95,"volume_trend":null,"price_change_pct":0.0,"crash_score":false,"spark_process_time":1775580781791,"latency_ms":5442698},{"symbol":"COST","sector":"Consumer","open":1012.53,"high":1012.53,"low":1012.53,"close":1012.53,"volume":0,"timestamp":"2026-04-07 11:21:00","kafka_produce_time":1775575328915.0,"data_type":"real","event_time":"2026-04-07 11:21:00","date":"2026-04-07","_is_new":true,"moving_avg_5":1012.52,"moving_avg_20":1012.77,"volatility":0.0268,"rsi_14":47.25,"vwap":1014.95,"volume_trend":null,"price_change_pct":0.0,"crash_score":false,"spark_process_time":1775580781791,"latency_ms":5452876},{"symbol":"COST","sector":"Consumer","open":1012.53,"high":1012.53,"low":1012.53,"close":1012.53,"volume":0,"timestamp":"2026-04-07 11:21:00","kafka_produce_time":1775575373945.0,"data_type":"real","event_time":"2026-04-07 11:21:00","date":"2026-04-07","_is_new":true,"moving_avg_5":1012.52,"moving_avg_20":1012.75,"volatility":0.0268,"rsi_14":47.25,"vwap":1014.95,"volume_trend":null,"price_change_pct":0.0,"crash_score":false,"spark_process_time":1775580781791,"latency_ms":5407846},{"symbol":"COST","sector":"Consumer","open":1012.53,"high":1012.53,"low":1012.53,"close":1012.53,"volume":0,"timestamp":"2026-04-07 11:21:00","kafka_produce_time":1775575343939.0,"data_type":"real","event_time":"2026-04-07 11:21:00","date":"2026-04-07","_is_new":true,"moving_avg_5":1012.53,"moving_avg_20":1012.74,"volatility":0.0,"rsi_14":47.25,"vwap":1014.95,"volume_trend":null,"price_change_pct":0.0,"crash_score":false,"spark_process_time":1775580781791,"latency_ms":5437852},{"symbol":"COST","sector":"Consumer","open":1012.53,"high":1012.53,"low":1012.53,"close":1012.53,"volume":0,"timestamp":"2026-04-07 11:21:00","kafka_produce_time":1775575303931.0,"data_type":"real","event_time":"2026-04-07 11:21:00","date":"2026-04-07","_is_new":true,"moving_avg_5":1012.53,"moving_avg_20":1012.71,"volatility":0.0,"rsi_14":47.25,"vwap":1014.95,"volume_trend":null,"price_change_pct":0.0,"crash_score":false,"spark_process_time":1775580781791,"latency_ms":5477860},{"symbol":"COST","sector":"Consumer","open":1012.47,"high":1012.47,"low":1012.47,"close":1012.47,"volume":0,"timestamp":"2026-04-07 11:21:00","kafka_produce_time":1775575294168.0,"data_type":"real","event_time":"2026-04-07 11:21:00","date":"2026-04-07","_is_new":true,"moving_avg_5":1012.52,"moving_avg_20":1012.7,"volatility":0.0268,"rsi_14":45.55,"vwap":1014.95,"volume_trend":null,"price_change_pct":0.0,"crash_score":false,"spark_process_time":1775580781791,"latency_ms":5487623},{"symbol":"COST","sector":"Consumer","open":1012.53,"high":1012.53,"low":1012.53,"close":1012.53,"volume":0,"timestamp":"2026-04-07 11:21:00","kafka_produce_time":1775575308952.0,"data_type":"real","event_time":"2026-04-07 11:21:00","date":"2026-04-07","_is_new":true,"moving_avg_5":1012.52,"moving_avg_20":1012.69,"volatility":0.0268,"rsi_14":47.58,"vwap":1014.95,"volume_trend":null,"price_change_pct":0.0,"crash_score":false,"spark_process_time":1775580781791,"latency_ms":5472839},{"symbol":"COST","sector":"Consumer","open":1012.53,"high":1012.53,"low":1012.53,"close":1012.53,"volume":0,"timestamp":"2026-04-07 11:21:00","kafka_produce_time":1775575313818.0,"data_type":"real","event_time":"2026-04-07 11:21:00","date":"2026-04-07","_is_new":true,"moving_avg_5":1012.52,"moving_avg_20":1012.67,"volatility":0.0268,"rsi_14":47.58,"vwap":1014.95,"volume_trend":null,"price_change_pct":0.0,"crash_score":false,"spark_process_time":1775580781791,"latency_ms":5467973},{"symbol":"COST","sector":"Consumer","open":1012.53,"high":1012.53,"low":1012.53,"close":1012.53,"volume":0,"timestamp":"2026-04-07 11:21:00","kafka_produce_time":1775575334003.0,"data_type":"real","event_time":"2026-04-07 11:21:00","date":"2026-04-07","_is_new":true,"moving_avg_5":1012.52,"moving_avg_20":1012.63,"volatility":0.0268,"rsi_14":47.58,"vwap":1014.95,"volume_trend":null,"price_change_pct":0.0,"crash_score":false,"spark_process_time":1775580781791,"latency_ms":5447788},{"symbol":"COST","sector":"Consumer","open":1012.53,"high":1012.53,"low":1012.53,"close":1012.53,"volume":0,"timestamp":"2026-04-07 11:21:00","kafka_produce_time":1775575323877.0,"data_type":"real","event_time":"2026-04-07 11:21:00","date":"2026-04-07","_is_new":true,"moving_avg_5":1012.52,"moving_avg_20":1012.6,"volatility":0.0268,"rsi_14":47.58,"vwap":1014.95,"volume_trend":null,"price_change_pct":0.0,"crash_score":false,"spark_process_time":1775580781791,"latency_ms":5457914},{"symbol":"COST","sector":"Consumer","open":1012.51,"high":1012.51,"low":1012.51,"close":1012.51,"volume":0,"timestamp":"2026-04-07 11:22:00","kafka_produce_time":1775575399008.0,"data_type":"real","event_time":"2026-04-07 11:22:00","date":"2026-04-07","_is_new":true,"moving_avg_5":1012.53,"moving_avg_20":1012.57,"volatility":0.0089,"rsi_14":46.8,"vwap":1014.95,"volume_trend":null,"price_change_pct":0.0,"crash_score":false,"spark_process_time":1775580781791,"latency_ms":5382783},{"symbol":"COST","sector":"Consumer","open":1012.51,"high":1012.51,"low":1012.51,"close":1012.51,"volume":0,"timestamp":"2026-04-07 11:22:00","kafka_produce_time":1775575384009.0,"data_type":"real","event_time":"2026-04-07 11:22:00","date":"2026-04-07","_is_new":true,"moving_avg_5":1012.52,"moving_avg_20":1012.53,"volatility":0.011,"rsi_14":46.8,"vwap":1014.95,"volume_trend":null,"price_change_pct":0.0,"crash_score":false,"spark_process_time":1775580781791,"latency_ms":5397782},{"symbol":"COST","sector":"Consumer","open":1012.51,"high":1012.51,"low":1012.51,"close":1012.51,"volume":0,"timestamp":"2026-04-07 11:22:00","kafka_produce_time":1775575379114.0,"data_type":"real","event_time":"2026-04-07 11:22:00","date":"2026-04-07","_is_new":true,"moving_avg_5":1012.52,"moving_avg_20":1012.52,"volatility":0.011,"rsi_14":46.8,"vwap":1014.95,"volume_trend":null,"price_change_pct":0.0,"crash_score":false,"spark_process_time":1775580781791,"latency_ms":5402677},{"symbol":"COST","sector":"Consumer","open":1012.51,"high":1012.51,"low":1012.51,"close":1012.51,"volume":0,"timestamp":"2026-04-07 11:22:00","kafka_produce_time":1775575394135.0,"data_type":"real","event_time":"2026-04-07 11:22:00","date":"2026-04-07","_is_new":true,"moving_avg_5":1012.51,"moving_avg_20":1012.52,"volatility":0.0089,"rsi_14":46.8,"vwap":1014.95,"volume_trend":null,"price_change_pct":0.0,"crash_score":false,"spark_process_time":1775580781791,"latency_ms":5387656},{"symbol":"COST","sector":"Consumer","open":1012.51,"high":1012.51,"low":1012.51,"close":1012.51,"volume":0,"timestamp":"2026-04-07 11:22:00","kafka_produce_time":1775575389224.0,"data_type":"real","event_time":"2026-04-07 11:22:00","date":"2026-04-07","_is_new":true,"moving_avg_5":1012.51,"moving_avg_20":1012.52,"volatility":0.0,"rsi_14":46.8,"vwap":1014.95,"volume_trend":null,"price_change_pct":0.0,"crash_score":false,"spark_process_time":1775580781791,"latency_ms":5392567},{"symbol":"COST","sector":"Consumer","open":1012.08,"high":1012.08,"low":1012.08,"close":1012.08,"volume":0,"timestamp":"2026-04-07 11:23:00","kafka_produce_time":1775575474174.0,"data_type":"real","event_time":"2026-04-07 11:23:00","date":"2026-04-07","_is_new":true,"moving_avg_5":1012.42,"moving_avg_20":1012.5,"volatility":0.1923,"rsi_14":30.93,"vwap":1014.95,"volume_trend":null,"price_change_pct":0.0,"crash_score":false,"spark_process_time":1775580781791,"latency_ms":5307617},{"symbol":"COST","sector":"Consumer","open":1012.08,"high":1012.08,"low":1012.08,"close":1012.08,"volume":0,"timestamp":"2026-04-07 11:23:00","kafka_produce_time":1775575419064.0,"data_type":"real","event_time":"2026-04-07 11:23:00","date":"2026-04-07","_is_new":true,"moving_avg_5":1012.34,"moving_avg_20":1012.47,"volatility":0.2355,"rsi_14":30.93,"vwap":1014.95,"volume_trend":null,"price_change_pct":0.0,"crash_score":false,"spark_process_time":1775580781791,"latency_ms":5362727},{"symbol":"COST","sector":"Consumer","open":1012.08,"high":1012.08,"low":1012.08,"close":1012.08,"volume":0,"timestamp":"2026-04-07 11:23:00","kafka_produce_time":1775575434085.0,"data_type":"real","event_time":"2026-04-07 11:23:00","date":"2026-04-07","_is_new":true,"moving_avg_5":1012.25,"moving_avg_20":1012.45,"volatility":0.2355,"rsi_14":30.93,"vwap":1014.95,"volume_trend":null,"price_change_pct":0.0,"crash_score":false,"spark_process_time":1775580781791,"latency_ms":5347706},{"symbol":"COST","sector":"Consumer","open":1012.08,"high":1012.08,"low":1012.08,"close":1012.08,"volume":0,"timestamp":"2026-04-07 11:23:00","kafka_produce_time":1775575429061.0,"data_type":"real","event_time":"2026-04-07 11:23:00","date":"2026-04-07","_is_new":true,"moving_avg_5":1012.17,"moving_avg_20":1012.43,"volatility":0.1923,"rsi_14":30.93,"vwap":1014.95,"volume_trend":null,"price_change_pct":0.0,"crash_score":false,"spark_process_time":1775580781791,"latency_ms":5352730},{"symbol":"COST","sector":"Consumer","open":1012.08,"high":1012.08,"low":1012.08,"close":1012.08,"volume":0,"timestamp":"2026-04-07 11:23:00","kafka_produce_time":1775575469097.0,"data_type":"real","event_time":"2026-04-07 11:23:00","date":"2026-04-07","_is_new":true,"moving_avg_5":1012.08,"moving_avg_20":1012.41,"volatility":0.0,"rsi_14":30.93,"vwap":1014.95,"volume_trend":null,"price_change_pct":0.0,"crash_score":false,"spark_process_time":1775580781791,"latency_ms":5312694},{"symbol":"COST","sector":"Consumer","open":1012.47,"high":1012.47,"low":1012.47,"close":1012.47,"volume":0,"timestamp":"2026-04-07 11:23:00","kafka_produce_time":1775575404029.0,"data_type":"real","event_time":"2026-04-07 11:23:00","date":"2026-04-07","_is_new":true,"moving_avg_5":1012.16,"moving_avg_20":1012.41,"volatility":0.1744,"rsi_14":52.22,"vwap":1014.95,"volume_trend":null,"price_change_pct":0.0,"crash_score":false,"spark_process_time":1775580781791,"latency_ms":5377762},{"symbol":"COST","sector":"Consumer","open":1012.08,"high":1012.08,"low":1012.08,"close":1012.08,"volume":0,"timestamp":"2026-04-07 11:23:00","kafka_produce_time":1775575424193.0,"data_type":"real","event_time":"2026-04-07 11:23:00","date":"2026-04-07","_is_new":true,"moving_avg_5":1012.16,"moving_avg_20":1012.38,"volatility":0.1744,"rsi_14":39.21,"vwap":1014.95,"volume_trend":null,"price_change_pct":0.0,"crash_score":false,"spark_process_time":1775580781791,"latency_ms":5357598},{"symbol":"COST","sector":"Consumer","open":1012.08,"high":1012.08,"low":1012.08,"close":1012.08,"volume":0,"timestamp":"2026-04-07 11:23:00","kafka_produce_time":1775575464171.0,"data_type":"real","event_time":"2026-04-07 11:23:00","date":"2026-04-07","_is_new":true,"moving_avg_5":1012.16,"moving_avg_20":1012.36,"volatility":0.1744,"rsi_14":39.21,"vwap":1014.95,"volume_trend":null,"price_change_pct":0.0,"crash_score":false,"spark_process_time":1775580781791,"latency_ms":5317620},{"symbol":"COST","sector":"Consumer","open":1012.08,"high":1012.08,"low":1012.08,"close":1012.08,"volume":0,"timestamp":"2026-04-07 11:23:00","kafka_produce_time":1775575454169.0,"data_type":"real","event_time":"2026-04-07 11:23:00","date":"2026-04-07","_is_new":true,"moving_avg_5":1012.16,"moving_avg_20":1012.34,"volatility":0.1744,"rsi_14":39.21,"vwap":1014.95,"volume_trend":null,"price_change_pct":0.0,"crash_score":false,"spark_process_time":1775580781791,"latency_ms":5327622},{"symbol":"COST","sector":"Consumer","open":1012.08,"high":1012.08,"low":1012.08,"close":1012.08,"volume":0,"timestamp":"2026-04-07 11:23:00","kafka_produce_time":1775575479201.0,"data_type":"real","event_time":"2026-04-07 11:23:00","date":"2026-04-07","_is_new":true,"moving_avg_5":1012.16,"moving_avg_20":1012.32,"volatility":0.1744,"rsi_14":39.21,"vwap":1014.95,"volume_trend":null,"price_change_pct":0.0,"crash_score":false,"spark_process_time":1775580781791,"latency_ms":5302590},{"symbol":"COST","sector":"Consumer","open":1012.08,"high":1012.08,"low":1012.08,"close":1012.08,"volume":0,"timestamp":"2026-04-07 11:23:00","kafka_produce_time":1775575484155.0,"data_type":"real","event_time":"2026-04-07 11:23:00","date":"2026-04-07","_is_new":true,"moving_avg_5":1012.08,"moving_avg_20":1012.3,"volatility":0.0,"rsi_14":39.21,"vwap":1014.95,"volume_trend":null,"price_change_pct":0.0,"crash_score":false,"spark_process_time":1775580781791,"latency_ms":5297636},{"symbol":"COST","sector":"Consumer","open":1012.08,"high":1012.08,"low":1012.08,"close":1012.08,"volume":0,"timestamp":"2026-04-07 11:23:00","kafka_produce_time":1775575444117.0,"data_type":"real","event_time":"2026-04-07 11:23:00","date":"2026-04-07","_is_new":true,"moving_avg_5":1012.08,"moving_avg_20":1012.27,"volatility":0.0,"rsi_14":39.21,"vwap":1014.95,"volume_trend":null,"price_change_pct":0.0,"crash_score":false,"spark_process_time":1775580781791,"latency_ms":5337674},{"symbol":"COST","sector":"Consumer","open":1012.47,"high":1012.47,"low":1012.47,"close":1012.47,"volume":0,"timestamp":"2026-04-07 11:23:00","kafka_produce_time":1775575409132.0,"data_type":"real","event_time":"2026-04-07 11:23:00","date":"2026-04-07","_is_new":true,"moving_avg_5":1012.16,"moving_avg_20":1012.27,"volatility":0.1744,"rsi_14":56.22,"vwap":1014.95,"volume_trend":null,"price_change_pct":0.0,"crash_score":false,"spark_process_time":1775580781791,"latency_ms":5372659},{"symbol":"COST","sector":"Consumer","open":1012.08,"high":1012.08,"low":1012.08,"close":1012.08,"volume":0,"timestamp":"2026-04-07 11:23:00","kafka_produce_time":1775575449098.0,"data_type":"real","event_time":"2026-04-07 11:23:00","date":"2026-04-07","_is_new":true,"moving_avg_5":1012.16,"moving_avg_20":1012.25,"volatility":0.1744,"rsi_14":43.2,"vwap":1014.95,"volume_trend":null,"price_change_pct":0.0,"crash_score":false,"spark_process_time":1775580781791,"latency_ms":5332693},{"symbol":"COST","sector":"Consumer","open":1012.08,"high":1012.08,"low":1012.08,"close":1012.08,"volume":0,"timestamp":"2026-04-07 11:23:00","kafka_produce_time":1775575459197.0,"data_type":"real","event_time":"2026-04-07 11:23:00","date":"2026-04-07","_is_new":true,"moving_avg_5":1012.16,"moving_avg_20":1012.23,"volatility":0.1744,"rsi_14":43.2,"vwap":1014.95,"volume_trend":null,"price_change_pct":0.0,"crash_score":false,"spark_process_time":1775580781791,"latency_ms":5322594},{"symbol":"COST","sector":"Consumer","open":1012.08,"high":1012.08,"low":1012.08,"close":1012.08,"volume":0,"timestamp":"2026-04-07 11:23:00","kafka_produce_time":1775575489290.0,"data_type":"real","event_time":"2026-04-07 11:23:00","date":"2026-04-07","_is_new":true,"moving_avg_5":1012.16,"moving_avg_20":1012.21,"volatility":0.1744,"rsi_14":43.2,"vwap":1014.95,"volume_trend":null,"price_change_pct":0.0,"crash_score":false,"spark_process_time":1775580781791,"latency_ms":5292501},{"symbol":"COST","sector":"Consumer","open":1012.08,"high":1012.08,"low":1012.08,"close":1012.08,"volume":0,"timestamp":"2026-04-07 11:23:00","kafka_produce_time":1775575494135.0,"data_type":"real","event_time":"2026-04-07 11:23:00","date":"2026-04-07","_is_new":true,"moving_avg_5":1012.16,"moving_avg_20":1012.18,"volatility":0.1744,"rsi_14":43.2,"vwap":1014.95,"volume_trend":null,"price_change_pct":0.0,"crash_score":false,"spark_process_time":1775580781791,"latency_ms":5287656},{"symbol":"COST","sector":"Consumer","open":1012.47,"high":1012.47,"low":1012.47,"close":1012.47,"volume":0,"timestamp":"2026-04-07 11:23:00","kafka_produce_time":1775575414046.0,"data_type":"real","event_time":"2026-04-07 11:23:00","date":"2026-04-07","_is_new":true,"moving_avg_5":1012.16,"moving_avg_20":1012.18,"volatility":0.1744,"rsi_14":56.69,"vwap":1014.95,"volume_trend":null,"price_change_pct":0.0,"crash_score":false,"spark_process_time":1775580781791,"latency_ms":5367745},{"symbol":"COST","sector":"Consumer","open":1012.08,"high":1012.08,"low":1012.08,"close":1012.08,"volume":0,"timestamp":"2026-04-07 11:23:00","kafka_produce_time":1775575439085.0,"data_type":"real","event_time":"2026-04-07 11:23:00","date":"2026-04-07","_is_new":true,"moving_avg_5":1012.16,"moving_avg_20":1012.16,"volatility":0.1744,"rsi_14":45.14,"vwap":1014.95,"volume_trend":null,"price_change_pct":0.0,"crash_score":false,"spark_process_time":1775580781791,"latency_ms":5342706},{"symbol":"COST","sector":"Consumer","open":1011.6,"high":1011.6,"low":1011.6,"close":1011.6,"volume":0,"timestamp":"2026-04-07 11:24:00","kafka_produce_time":1775575504285.0,"data_type":"real","event_time":"2026-04-07 11:24:00","date":"2026-04-07","_is_new":true,"moving_avg_5":1012.06,"moving_avg_20":1012.11,"volatility":0.3086,"rsi_14":35.55,"vwap":1014.95,"volume_trend":null,"price_change_pct":0.0,"crash_score":false,"spark_process_time":1775580781791,"latency_ms":5277506},{"symbol":"COST","sector":"Consumer","open":1011.6,"high":1011.6,"low":1011.6,"close":1011.6,"volume":0,"timestamp":"2026-04-07 11:24:00","kafka_produce_time":1775575499118.0,"data_type":"real","event_time":"2026-04-07 11:24:00","date":"2026-04-07","_is_new":true,"moving_avg_5":1011.97,"moving_avg_20":1012.09,"volatility":0.3701,"rsi_14":35.55,"vwap":1014.95,"volume_trend":null,"price_change_pct":0.0,"crash_score":false,"spark_process_time":1775580781791,"latency_ms":5282673},{"symbol":"COST","sector":"Consumer","open":1011.6,"high":1011.6,"low":1011.6,"close":1011.6,"volume":0,"timestamp":"2026-04-07 11:24:00","kafka_produce_time":1775575509057.0,"data_type":"real","event_time":"2026-04-07 11:24:00","date":"2026-04-07","_is_new":true,"moving_avg_5":1011.87,"moving_avg_20":1012.07,"volatility":0.3946,"rsi_14":35.55,"vwap":1014.95,"volume_trend":null,"price_change_pct":0.0,"crash_score":false,"spark_process_time":1775580781791,"latency_ms":5272734},{"symbol":"COST","sector":"Consumer","open":1011.6,"high":1011.6,"low":1011.6,"close":1011.6,"volume":0,"timestamp":"2026-04-07 11:25:00","kafka_produce_time":1775575514210.0,"data_type":"real","event_time":"2026-04-07 11:25:00","date":"2026-04-07","_is_new":true,"moving_avg_5":1011.7,"moving_avg_20":1012.04,"volatility":0.2147,"rsi_14":35.55,"vwap":1014.95,"volume_trend":null,"price_change_pct":0.0,"crash_score":false,"spark_process_time":1775580781791,"latency_ms":5267581},{"symbol":"COST","sector":"Consumer","open":1011.6,"high":1011.6,"low":1011.6,"close":1011.6,"volume":0,"timestamp":"2026-04-07 11:25:00","kafka_produce_time":1775575534234.0,"data_type":"real","event_time":"2026-04-07 11:25:00","date":"2026-04-07","_is_new":true,"moving_avg_5":1011.6,"moving_avg_20":1012.02,"volatility":0.0,"rsi_14":35.55,"vwap":1014.95,"volume_trend":null,"price_change_pct":0.0,"crash_score":false,"spark_process_time":1775580781791,"latency_ms":5247557},{"symbol":"COST","sector":"Consumer","open":1011.59,"high":1011.59,"low":1011.59,"close":1011.59,"volume":0,"timestamp":"2026-04-07 11:25:00","kafka_produce_time":1775575554220.0,"data_type":"real","event_time":"2026-04-07 11:25:00","date":"2026-04-07","_is_new":true,"moving_avg_5":1011.6,"moving_avg_20":1011.99,"volatility":0.0045,"rsi_14":35.32,"vwap":1014.95,"volume_trend":null,"price_change_pct":0.0,"crash_score":false,"spark_process_time":1775580781791,"latency_ms":5227571},{"symbol":"COST","sector":"Consumer","open":1011.59,"high":1011.59,"low":1011.59,"close":1011.59,"volume":0,"timestamp":"2026-04-07 11:25:00","kafka_produce_time":1775575559356.0,"data_type":"real","event_time":"2026-04-07 11:25:00","date":"2026-04-07","_is_new":true,"moving_avg_5":1011.6,"moving_avg_20":1011.95,"volatility":0.0055,"rsi_14":35.32,"vwap":1014.95,"volume_trend":null,"price_change_pct":0.0,"crash_score":false,"spark_process_time":1775580781791,"latency_ms":5222435},{"symbol":"COST","sector":"Consumer","open":1011.59,"high":1011.59,"low":1011.59,"close":1011.59,"volume":0,"timestamp":"2026-04-07 11:25:00","kafka_produce_time":1775575539222.0,"data_type":"real","event_time":"2026-04-07 11:25:00","date":"2026-04-07","_is_new":true,"moving_avg_5":1011.59,"moving_avg_20":1011.93,"volatility":0.0055,"rsi_14":35.32,"vwap":1014.95,"volume_trend":null,"price_change_pct":0.0,"crash_score":false,"spark_process_time":1775580781791,"latency_ms":5242569},{"symbol":"COST","sector":"Consumer","open":1011.6,"high":1011.6,"low":1011.6,"close":1011.6,"volume":0,"timestamp":"2026-04-07 11:25:00","kafka_produce_time":1775575524138.0,"data_type":"real","event_time":"2026-04-07 11:25:00","date":"2026-04-07","_is_new":true,"moving_avg_5":1011.59,"moving_avg_20":1011.9,"volatility":0.0055,"rsi_14":35.83,"vwap":1014.95,"volume_trend":null,"price_change_pct":0.0,"crash_score":false,"spark_process_time":1775580781791,"latency_ms":5257653},{"symbol":"COST","sector":"Consumer","open":1011.6,"high":1011.6,"low":1011.6,"close":1011.6,"volume":0,"timestamp":"2026-04-07 11:25:00","kafka_produce_time":1775575519256.0,"data_type":"real","event_time":"2026-04-07 11:25:00","date":"2026-04-07","_is_new":true,"moving_avg_5":1011.59,"moving_avg_20":1011.88,"volatility":0.0055,"rsi_14":35.83,"vwap":1014.95,"volume_trend":null,"price_change_pct":0.0,"crash_score":false,"spark_process_time":1775580781791,"latency_ms":5262535},{"symbol":"COST","sector":"Consumer","open":1011.59,"high":1011.59,"low":1011.59,"close":1011.59,"volume":0,"timestamp":"2026-04-07 11:25:00","kafka_produce_time":1775575565301.0,"data_type":"real","event_time":"2026-04-07 11:25:00","date":"2026-04-07","_is_new":true,"moving_avg_5":1011.59,"moving_avg_20":1011.85,"volatility":0.0055,"rsi_14":35.51,"vwap":1014.95,"volume_trend":null,"price_change_pct":0.0,"crash_score":false,"spark_process_time":1775580781791,"latency_ms":5216490},{"symbol":"COST","sector":"Consumer","open":1011.6,"high":1011.6,"low":1011.6,"close":1011.6,"volume":0,"timestamp":"2026-04-07 11:25:00","kafka_produce_time":1775575529379.0,"data_type":"real","event_time":"2026-04-07 11:25:00","date":"2026-04-07","_is_new":true,"moving_avg_5":1011.6,"moving_avg_20":1011.83,"volatility":0.0055,"rsi_14":36.13,"vwap":1014.95,"volume_trend":null,"price_change_pct":0.0,"crash_score":false,"spark_process_time":1775580781791,"latency_ms":5252412},{"symbol":"COST","sector":"Consumer","open":1011.59,"high":1011.59,"low":1011.59,"close":1011.59,"volume":0,"timestamp":"2026-04-07 11:25:00","kafka_produce_time":1775575549440.0,"data_type":"real","event_time":"2026-04-07 11:25:00","date":"2026-04-07","_is_new":true,"moving_avg_5":1011.6,"moving_avg_20":1011.8,"volatility":0.0055,"rsi_14":35.76,"vwap":1014.95,"volume_trend":null,"price_change_pct":0.0,"crash_score":false,"spark_process_time":1775580781791,"latency_ms":5232351},{"symbol":"COST","sector":"Consumer","open":1011.59,"high":1011.59,"low":1011.59,"close":1011.59,"volume":0,"timestamp":"2026-04-07 11:25:00","kafka_produce_time":1775575544388.0,"data_type":"real","event_time":"2026-04-07 11:25:00","date":"2026-04-07","_is_new":true,"moving_avg_5":1011.59,"moving_avg_20":1011.76,"volatility":0.0055,"rsi_14":35.76,"vwap":1014.95,"volume_trend":null,"price_change_pct":0.0,"crash_score":false,"spark_process_time":1775580781791,"latency_ms":5237403}]